Connnet/__init__.py
Connnet/network.py
Connet-0.1.1.dist-info/LICENSE.txt
Connet-0.1.1.dist-info/METADATA
Connet-0.1.1.dist-info/WHEEL
Connet-0.1.1.dist-info/entry_points.txt
Connet-0.1.1.dist-info/top_level.txt
Connet-0.1.1.dist-info/RECORD
