Metadata-Version: 2.1
Name: Connet
Version: 0.1.1
Summary: A package for generating network files
Author: Gongruihao
Author-email: 202031200039@mail.bnu.edu.cn
Classifier: Programming Language :: Python :: 3
Classifier: License :: OSI Approved :: Apache Software License
Classifier: Operating System :: OS Independent
Requires-Python: >=3.6
License-File: LICENSE.txt
Requires-Dist: pandas
Requires-Dist: openpyxl
